README.rst
setup.py
py_whoisxmlapi/__init__.py
py_whoisxmlapi/domainavailability.py
py_whoisxmlapi.egg-info/PKG-INFO
py_whoisxmlapi.egg-info/SOURCES.txt
py_whoisxmlapi.egg-info/dependency_links.txt
py_whoisxmlapi.egg-info/not-zip-safe
py_whoisxmlapi.egg-info/top_level.txt