Metadata-Version: 1.1
Name: py-whoisxmlapi
Version: 0.1.4
Summary: Python3 WhoisService data parser
Home-page: https://bitbucket.org/tvdsluijs/py_whoisxmlapi
Author: Theo van der Sluijs
Author-email: theo@vandersluijs.nl
License: CC BY-NC-SA 4.0
Keywords: whois domains
Platform: UNKNOWN
Classifier: Programming Language :: Python :: 3
Classifier: Programming Language :: Python :: 3.3
Classifier: Programming Language :: Python :: 3.4
Classifier: Programming Language :: Python :: 3.5
